MANIFEST.in
README.md
distribution_notes.txt
notes_sqlacodegen.txt
requirements.txt
requirements_tests.txt
setup.cfg
setup.py
odm2api/ODMconnection.py
odm2api/__init__.py
odm2api/base.py
odm2api.egg-info/PKG-INFO
odm2api.egg-info/SOURCES.txt
odm2api.egg-info/dependency_links.txt
odm2api.egg-info/requires.txt
odm2api.egg-info/top_level.txt
odm2api/ODM1_1_1/__init__.py
odm2api/ODM1_1_1/memory_database.py
odm2api/ODM1_1_1/models.py
odm2api/ODM1_1_1/services/__init__.py
odm2api/ODM1_1_1/services/edit_service.py
odm2api/ODM1_1_1/services/export_service.py
odm2api/ODM1_1_1/services/series_service.py
odm2api/ODM2/__init__.py
odm2api/ODM2/models.py
odm2api/ODM2/LikeODM1/__init__.py
odm2api/ODM2/LikeODM1/models.py
odm2api/ODM2/services/__init__.py
odm2api/ODM2/services/createService.py
odm2api/ODM2/services/deleteService.py
odm2api/ODM2/services/readService.py
odm2api/ODM2/services/updateService.py