Metadata-Version: 1.1
Name: odm2api
Version: 0.5.2
Summary: A Python-based application programmers interface for the Observations Data Model 2 (ODM2) 
Home-page: https://github.com/ODM2/ODM2PythonAPI
Author: David Valentine
Author-email: david.valentine@gmail.com
License: BSD-3-Clause
Keywords: Observations Data Model ODM2
Platform: UNKNOWN
Classifier: Development Status :: 3 - Alpha
Classifier: Intended Audience :: Developers
Classifier: Topic :: Software Development :: Build Tools
Classifier: License :: OSI Approved :: BSD License
Classifier: Operating System :: OS Independent
Classifier: Programming Language :: Python :: 2.7
Classifier: Topic :: Software Development :: Libraries :: Python Modules
Classifier: Topic :: Scientific/Engineering
